README.txt
setup.py
docs/HISTORY.txt
yaco/__init__.py
yaco.releaser.egg-info/PKG-INFO
yaco.releaser.egg-info/SOURCES.txt
yaco.releaser.egg-info/dependency_links.txt
yaco.releaser.egg-info/entry_points.txt
yaco.releaser.egg-info/namespace_packages.txt
yaco.releaser.egg-info/not-zip-safe
yaco.releaser.egg-info/requires.txt
yaco.releaser.egg-info/top_level.txt
yaco/releaser/__init__.py