Metadata-Version: 1.0
Name: yaco.releaser
Version: 0.1
Summary: Yaco addon to zest.releaser to include ticket referencce in commits
Home-page: http://svn.plone.org/svn/collective/
Author: Pablo Caro Revuelta
Author-email: pcaro@yaco.es
License: GPL
Platform: UNKNOWN
Classifier: Programming Language :: Python
Classifier: Topic :: Software Development :: Libraries :: Python Modules
